LEGEND.rst
MANIFEST.in
README.rst
setup.py
gperf/__init__.py
gperf/gperf.py
gperf.egg-info/PKG-INFO
gperf.egg-info/SOURCES.txt
gperf.egg-info/dependency_links.txt
gperf.egg-info/entry_points.txt
gperf.egg-info/top_level.txt