Metadata-Version: 1.1
Name: gperf
Version: 0.2
Summary: Graphing from sysstat sar data into time-based graph
Home-page: https://github.com/sakti/gperf
Author: Sakti Dwi Cahyono
Author-email: 54krpl at gmail dot com
License: BSD
Keywords: sar sysstat time-based graph
Platform: UNKNOWN
Classifier: Development Status :: 4 - Beta
Classifier: Environment :: Console
Classifier: Intended Audience :: System Administrators
Classifier: License :: OSI Approved :: BSD License
Classifier: Programming Language :: Python :: 2.6
Classifier: Programming Language :: Python :: 2.7
Classifier: Topic :: Multimedia :: Graphics :: Graphics Conversion
